{
  "eventTitle": "JAWS-UG 配信部 #50 LT大会",
  "chapterName": "JAWS-UG 配信部",
  "speakers": [
    {
      "talkTitle": "AWS Lambda の最新アップデートについて",
      "speakers": [
        {
          "name": "山田 太郎",
          "affiliation": "株式会社配信テック",
          "photoUrl": "speaker-placeholder.svg"
        }
      ]
    },
    {
      "talkTitle": "Amazon S3 コスト最適化の実践",
      "speakers": [
        {
          "name": "鈴木 花子",
          "affiliation": "配信スタート株式会社",
          "photoUrl": "speaker-placeholder.svg"
        },
        {
          "name": "佐藤 一郎",
          "affiliation": "株式会社デジタ配信",
          "photoUrl": "speaker-placeholder.svg"
        }
      ]
    },
    {
      "talkTitle": "AgentCoretとは? 最新の動向を紹介",
      "speakers": [
        {
          "name": "Abc edf",
          "affiliation": "配信スタート株式会社",
          "photoUrl": "speaker-placeholder.svg"
        },
        {
          "name": "佐藤 次郎",
          "affiliation": "株式会社デジタ配信",
          "photoUrl": "speaker-placeholder.svg"
        }
      ]
    },
    {
      "talkTitle": "ECS on Fargate で実現するサーバーレスコンテナ",
      "speakers": [
        {
          "name": "田中 美咲",
          "affiliation": "配信合同会社",
          "photoUrl": "speaker-placeholder.svg"
        },
        {
          "name": "高橋 健太",
          "affiliation": "株式会社配信ラボ",
          "photoUrl": "speaker-placeholder.svg"
        },
        {
          "name": "渡辺 さくら",
          "affiliation": "配信フリーランス",
          "photoUrl": "speaker-placeholder.svg"
        }
      ]
    }
  ],
  "hashtag": "#jawsug_tokyo",
  "musicLicense": {
    "title": "Sunny Days",
    "artist": "Sample Artist",
    "licenseType": "CC BY 4.0",
    "url": "https://example.com/license"
  },
  "theme": {
    "backgroundColor": "#1a1a2e",
    "accentColor": "#FF9900",
    "textColor": "#ffffff",
    "mutedTextColor": "#a0a0b0",
    "gradientFrom": "#0f0f23",
    "gradientTo": "#16213e"
  },
  "introEffect": "scaleIn",
  "titleEffect": "springScale",
  "speakerEffect": "springCards",
  "hashtagEffect": "springBounce",
  "licenseEffect": "fadeIn"
}
